npscoder/__init__.py
npscoder/main.py
npscoder/plot.py
npscoder/stats.py
npscoder-0.1.0.dist-info/LICENSE
npscoder-0.1.0.dist-info/METADATA
npscoder-0.1.0.dist-info/WHEEL
npscoder-0.1.0.dist-info/top_level.txt
npscoder-0.1.0.dist-info/RECORD
