Metadata-Version: 2.1
Name: npscoder
Version: 0.1.0
Summary: Non Parametric Supervised Coder
Author: Benoit Rognier
License: MIT
Requires-Python: >=3.13
License-File: LICENSE
Requires-Dist: pandas
Requires-Dist: numpy
Requires-Dist: typing
Requires-Dist: typing-extensions
Requires-Dist: IPython
Requires-Dist: matplotlib
Requires-Dist: scipy
Requires-Dist: statsmodels
Requires-Dist: python-dateutil
Requires-Dist: pandas
Requires-Dist: numpy
Requires-Dist: dataclasses
